pair_ai/__init__.py
pair_ai/context_loader.py
pair_ai/exceptions.py
pair_ai/extract.py
pair_ai/github_api.py
pair_ai/pair.py
pair_ai/pairwise.py
pair_ai/pdf_text.py
pair_ai/retry.py
pair_ai-0.5.16.dist-info/LICENSE
pair_ai-0.5.16.dist-info/METADATA
pair_ai-0.5.16.dist-info/WHEEL
pair_ai-0.5.16.dist-info/entry_points.txt
pair_ai-0.5.16.dist-info/top_level.txt
pair_ai-0.5.16.dist-info/RECORD
